MANIFEST.in
README.md
setup.py
src/dt_data_api/__init__.py
src/dt_data_api/api.py
src/dt_data_api/client.py
src/dt_data_api/constants.py
src/dt_data_api/exceptions.py
src/dt_data_api/logging.py
src/dt_data_api/storage.py
src/dt_data_api/utils.py
src/dt_data_api_ente.egg-info/PKG-INFO
src/dt_data_api_ente.egg-info/SOURCES.txt
src/dt_data_api_ente.egg-info/dependency_links.txt
src/dt_data_api_ente.egg-info/entry_points.txt
src/dt_data_api_ente.egg-info/requires.txt
src/dt_data_api_ente.egg-info/top_level.txt