Metadata-Version: 1.0
Name: dt-data-api-ente
Version: 0.1.13
Summary: UNKNOWN
Home-page: http://github.com/duckietown/lib-dt-data-api
Author: Andrea F. Daniele
Author-email: afdaniele@ttic.edu
License: UNKNOWN
Platform: UNKNOWN
